gw_foresight/__init__.py
gw_foresight/foresight.py
gw_foresight/library.py
gw_foresight/utils.py
gw_foresight-0.3.0.dist-info/METADATA
gw_foresight-0.3.0.dist-info/WHEEL
gw_foresight-0.3.0.dist-info/top_level.txt
gw_foresight-0.3.0.dist-info/RECORD
