Metadata-Version: 2.1
Name: gw-foresight
Version: 0.3.0
Summary: Glasswall Foresight API Python Wrapper
Author: Glasswall
Author-email: support@glasswall.com
Classifier: Programming Language :: Python :: 3
Classifier: Operating System :: OS Independent
Requires-Python: >=3.6
